xenoform/__init__.py
xenoform/compile.py
xenoform/config.py
xenoform/cppmodule.py
xenoform/errors.py
xenoform/extension_types.py
xenoform/logger.py
xenoform/py.typed
xenoform/utils.py
xenoform-0.1.7.dist-info/METADATA
xenoform-0.1.7.dist-info/WHEEL
xenoform-0.1.7.dist-info/licenses/LICENCE.md
xenoform-0.1.7.dist-info/RECORD
