Metadata-Version: 2.4
Name: xenoform
Version: 0.1.7
Summary: Inlined C++ functions
Project-URL: Homepage, https://github.com/virgesmith/xenoform
Project-URL: Bug Tracker, https://github.com/virgesmith/xenoform/issues
Author-email: virgesmith <andrew@friarswood.net>
License-Expression: MIT
License-File: LICENCE.md
Classifier: Operating System :: OS Independent
Classifier: Programming Language :: Python :: 3.12
Classifier: Programming Language :: Python :: 3.13
Classifier: Programming Language :: Python :: 3.14
Requires-Python: >=3.12
Requires-Dist: clang-format>=21.1.8
Requires-Dist: itrx>=0.2.1
Requires-Dist: numpy>=2.3.2
Requires-Dist: pybind11>=3.0.0
Requires-Dist: pydantic-settings>=2.12.0
Requires-Dist: setuptools>=80.9.0
Requires-Dist: types-setuptools>=80.9.0.20250529
Provides-Extra: examples
Requires-Dist: pandas-stubs>=2.3.0.250703; extra == 'examples'
Requires-Dist: pandas>=2.3.1; extra == 'examples'
